yang.connector-25.9-py3.13-nspkg.pth
yang/connector/__init__.py
yang/connector/gnmi.py
yang/connector/netconf.py
yang/connector/settings.py
yang/connector/xpath_util.py
yang/connector/grpc/__init__.py
yang/connector/grpc/telegraf.py
yang/connector/proto/__init__.py
yang/connector/proto/gnmi_ext_pb2.py
yang/connector/proto/gnmi_ext_pb2_grpc.py
yang/connector/proto/gnmi_pb2.py
yang/connector/proto/gnmi_pb2_grpc.py
yang/connector/tests/__init__.py
yang/connector/tests/test_gnmi.py
yang/connector/tests/test_grpc.py
yang/connector/tests/test_yang.py
yang.connector-25.9.dist-info/METADATA
yang.connector-25.9.dist-info/WHEEL
yang.connector-25.9.dist-info/namespace_packages.txt
yang.connector-25.9.dist-info/top_level.txt
yang.connector-25.9.dist-info/RECORD
